Workbook

Sheet Sources
A1: Sources et conventions
A2: Projet finance Michelin, donnees collectees au 20 avril 2026
A4: Source | B4: Donnee utilisee | C4: Lien / fichier
A5: Michelin | B5: Financial information at December 31, 2025 | C5: https://www.michelin.com/en/publications/group/financial-information-december-31-2025
A6: Michelin | B6: All Michelin key figures 2020-2025 | C6: sources/michelin_key_figures_2020_2025.xlsx
A7: Michelin | B7: 2025 Annual Results Guide | C7: sources/michelin_2025_annual_results_guide.pdf
A8: Michelin | B8: 2025 Universal Registration Document | C8: sources/michelin_2025_urd.pdf
A9: Grand View Research | B9: Global tires market 2025-2030 | C9: https://www.grandviewresearch.com/industry-analysis/tires-market-report
A10: StockAnalysis | B10: Michelin and peer valuation statistics | C10: https://stockanalysis.com/quote/epa/ML/statistics/
A11: CountryEconomy | B11: France 10-year bond yield | C11: https://countryeconomy.com/bonds/france
A12: Kroll | B12: Eurozone equity risk premium | C12: https://www.kroll.com/en/reports/cost-of-capital/recommended-eurozone-equity-risk-premium-corresponding-risk-free-rates
A14: Convention | B14: Valeur
A15: Unite des etats financiers | B15: EUR millions sauf indication contraire
A16: Cours de reference Michelin | B16: 32.24
A17: Actions diluees / en circulation | B17: 684.74m
A18: Recommandation retenue | B18: Acheter

Sheet Historical
A1: Historique financier Michelin
A2: Source: fichier officiel Michelin key figures 2020-2025
B3: 2020 | C3: 2021 | D3: 2022 | E3: 2023 | F3: 2024 | G3: 2025
A4: Chiffre d'affaires | B4: 20469 | C4: 23795 | D4: 28590 | E4: 28343 | F4: 27193 | G4: 25992.177
A5: Croissance CA | B5: -0.152 | C5: =(C4-B4)/B4 -> 0.16248962 | D5: =(D4-C4)/C4 -> 0.20151292 | E5: =(E4-D4)/D4 -> -0.0086393844 | F5: =(F4-E4)/E4 -> -0.040574392 | G5: =(G4-F4)/F4 -> -0.044159267
A6: Segment EBITDA | B6: 3631 | C6: 4700 | D6: 5262 | E6: 5489 | F6: 5361.0313 | G6: 4662.7121
A7: Marge EBITDA | B7: =B6/B4 -> 0.1773902 | C7: =C6/C4 -> 0.19752049 | D7: =D6/D4 -> 0.18405037 | E7: =E6/E4 -> 0.19366334 | F7: =F6/F4 -> 0.19714747 | G7: =G6/G4 -> 0.17938905
A8: Resultat operationnel des secteurs | B8: 1878 | C8: 2966 | D8: 3396 | E8: 3572 | F8: 3378 | G8: 2719.2186
A9: Marge operationnelle secteurs | B9: =B8/B4 -> 0.091748498 | C9: =C8/C4 -> 0.12464804 | D9: =D8/D4 -> 0.11878279 | E9: =E8/E4 -> 0.12602759 | F9: =F8/F4 -> 0.12422315 | G9: =G8/G4 -> 0.10461681
A10: Resultat operationnel | B10: 1403 | C10: 2777 | D10: 3021 | E10: 2652 | F10: 2631 | G10: 2366.1294
A11: Resultat net | B11: 625 | C11: 1845 | D11: 2009 | E11: 1983 | F11: 1890 | G11: 1663.968
A12: Marge nette | B12: =B11/B4 -> 0.030533978 | C12: =C11/C4 -> 0.077537298 | D12: =D11/D4 -> 0.070269325 | E12: =E11/E4 -> 0.069964365 | F12: =F11/F4 -> 0.069503181 | G12: =G11/G4 -> 0.06401803
A13: Cash-flow operationnel | B13: 3366 | C13: 2906 | D13: 1931 | E13: 5287 | F13: 4336 | G13: 3819.4142
A14: Capex | B14: 1221 | C14: 1705 | D14: 2141 | E14: 2236 | F14: 2182 | G14: 1967
A15: Capex / CA | B15: =B14/B4 -> 0.05965118 | C15: =C14/C4 -> 0.071653709 | D15: =D14/D4 -> 0.074886324 | E15: =E14/E4 -> 0.078890731 | F15: =F14/F4 -> 0.080241239 | G15: =G14/G4 -> 0.075676616
A16: Free cash-flow | B16: 2004 | C16: 1357 | D16: -180.3 | E16: 2342.8 | F16: 2225.4 | G16: 2181
A17: FCF / CA | B17: =B16/B4 -> 0.097904148 | C17: =C16/C4 -> 0.057028788 | D17: =D16/D4 -> -0.0063064008 | E17: =E16/E4 -> 0.082658858 | F17: =F16/F4 -> 0.081837238 | G17: =G16/G4 -> 0.083909862
A18: Dette nette | B18: 3531 | C18: 2789 | D18: 4320 | E18: 3280.8 | F18: 3112 | G18: 2345
A19: Dette nette / EBITDA | B19: =B18/B6 -> 0.97245938 | C19: =C18/C6 -> 0.59340426 | D19: =D18/D6 -> 0.82098062 | E19: =E18/E6 -> 0.5977045 | F19: =F18/F6 -> 0.58048533 | G19: =G18/G6 -> 0.50292619

Sheet Forecast
A1: Projection 2026E-2030E
A2: Scenario central: reprise graduelle des volumes, mix premium et discipline cash
B3: 2026E | C3: 2027E | D3: 2028E | E3: 2029E | F3: 2030E
A4: Chiffre d'affaires | B4: =Historical!G4*(1+B5) -> 26382.06 | C4: =B4*(1+C5) -> 27041.611 | D4: =C4*(1+D5) -> 27852.86 | E4: =D4*(1+E5) -> 28688.445 | F4: =E4*(1+F5) -> 29405.656
A5: Croissance CA | B5: 0.015 | C5: 0.025 | D5: 0.03 | E5: 0.03 | F5: 0.025
A6: Marge EBITDA | B6: 0.18 | C6: 0.184 | D6: 0.187 | E6: 0.189 | F6: 0.19
A7: EBITDA | B7: =B4*B6 -> 4748.7707 | C7: =C4*C6 -> 4975.6565 | D7: =D4*D6 -> 5208.4847 | E7: =E4*E6 -> 5422.1162 | F7: =F4*F6 -> 5587.0747
A8: Marge EBIT secteurs | B8: 0.107 | C8: 0.112 | D8: 0.116 | E8: 0.119 | F8: 0.12
A9: EBIT secteurs | B9: =B4*B8 -> 2822.8804 | C9: =C4*C8 -> 3028.6605 | D9: =D4*D8 -> 3230.9317 | E9: =E4*E8 -> 3413.925 | F9: =F4*F8 -> 3528.6788
A10: Taux d'impot | B10: 0.26293176 | C10: 0.26293176 | D10: 0.26293176 | E10: 0.26293176 | F10: 0.26293176
A11: NOPAT | B11: =B9*(1-B10) -> 2080.6555 | C11: =C9*(1-C10) -> 2232.3294 | D11: =D9*(1-D10) -> 2381.4171 | E11: =E9*(1-E10) -> 2516.2957 | F11: =F9*(1-F10) -> 2600.877
A12: D&A / CA | B12: 0.073 | C12: 0.072 | D12: 0.071 | E12: 0.07 | F12: 0.07
A13: D&A | B13: =B4*B12 -> 1925.8904 | C13: =C4*C12 -> 1946.996 | D13: =D4*D12 -> 1977.553 | E13: =E4*E12 -> 2008.1912 | F13: =F4*F12 -> 2058.396
A14: Capex / CA | B14: 0.073 | C14: 0.072 | D14: 0.071 | E14: 0.07 | F14: 0.07
A15: Capex | B15: =B4*B14 -> 1925.8904 | C15: =C4*C14 -> 1946.996 | D15: =D4*D14 -> 1977.553 | E15: =E4*E14 -> 2008.1912 | F15: =F4*F14 -> 2058.396
A16: Variation BFR | B16: =(B4-Historical!G4)*0.01 -> 3.8988266 | C16: =(C4-B4)*0.01 -> 6.5955149 | D16: =(D4-C4)*0.01 -> 8.1124834 | E16: =(E4-D4)*0.01 -> 8.3558579 | F16: =(F4-E4)*0.01 -> 7.1721113
A17: FCFF | B17: =B11+B13-B15-B16 -> 2076.7566 | C17: =C11+C13-C15-C16 -> 2225.7339 | D17: =D11+D13-D15-D16 -> 2373.3047 | E17: =E11+E13-E15-E16 -> 2507.9398 | F17: =F11+F13-F15-F16 -> 2593.7049

Sheet Comps
A1: Comparables boursiers
A2: Multiples de marche ponctuels au 20 avril 2026 ou derniere cloture disponible
A4: Societe | B4: Ticker | C4: Pays | D4: Justification | E4: EV/CA | F4: EV/EBITDA | G4: EV/EBIT
A5: Bridgestone | B5: TYO:5108 | C5: Japon | D5: Leader mondial pneus, exposition replacement/OE comparable | E5: 1.01 | F5: 5.38 | G5: 9.34
A6: Goodyear | B6: NASDAQ:GT | C6: Etats-Unis | D6: Pneumatiques purs, mais levier et marge faible | E6: 0.46 | F6: 6.8 | G6: 23.48
A7: Continental | B7: ETR:CON | C7: Allemagne | D7: Equipementier auto diversifie avec activite pneus | E7: 0.97 | F7: 6.89 | G7: 12.18
A8: Pirelli | B8: BIT:PIRC | C8: Italie | D8: Pneus premium, forte proximite avec Michelin en mix | E8: 1.18 | F8: 4.96 | G8: 7.78
A9: Yokohama Rubber | B9: TYO:5101 | C9: Japon | D9: Pneus et caoutchouc industriel, exposition Asie | E9: 1.22 | F9: 6.53 | G9: 9.6
A10: Hankook Tire | B10: KRX:161390 | C10: Coree du Sud | D10: Pneus mondiaux, positionnement valeur/premium | E10: 0.61 | F10: 4.03 | G10: 7.07
A12: Application 2026E | B12: Multiple bas | C12: Multiple median | D12: Multiple haut | E12: Prix bas | F12: Prix median | G12: Prix haut
A13: EV / CA | B13: =QUARTILE(E5:E10, 1) -> 0.7 | C13: =MEDIAN(E5:E10) -> 0.99 | D13: =QUARTILE(E5:E10, 3) -> 1.1375 | E13: =(B13*Forecast!$B$4-WACC!$B$8)/WACC!$B$6 -> 23.545348 | F13: =(C13*Forecast!$B$4-WACC!$B$8)/WACC!$B$6 -> 34.718636 | G13: =(D13*Forecast!$B$4-WACC!$B$8)/WACC!$B$6 -> 40.401602
A14: EV / EBITDA | B14: =QUARTILE(F5:F10, 1) -> 5.065 | C14: =MEDIAN(F5:F10) -> 5.955 | D14: =QUARTILE(F5:F10, 3) -> 6.7325 | E14: =(B14*Forecast!$B$7-WACC!$B$8)/WACC!$B$6 -> 31.701849 | F14: =(C14*Forecast!$B$7-WACC!$B$8)/WACC!$B$6 -> 37.874127 | G14: =(D14*Forecast!$B$7-WACC!$B$8)/WACC!$B$6 -> 43.266202
A15: EV / EBIT | B15: =QUARTILE(G5:G10, 1) -> 8.17 | C15: =MEDIAN(G5:G10) -> 9.47 | D15: =QUARTILE(G5:G10, 3) -> 11.535 | E15: =(B15*Forecast!$B$9-WACC!$B$8)/WACC!$B$6 -> 30.256642 | F15: =(C15*Forecast!$B$9-WACC!$B$8)/WACC!$B$6 -> 35.615967 | G15: =(D15*Forecast!$B$9-WACC!$B$8)/WACC!$B$6 -> 44.129049

Sheet WACC
A1: Calcul du WACC
A2: Approche CAPM et structure de capital de marche
A4: Input | B4: Valeur | C4: Unite
A5: Cours Michelin | B5: 32.24 | C5: EUR/action
A6: Actions en circulation | B6: 684.74 | C6: m
A7: Capitalisation boursiere | B7: =B5*B6 -> 22076.018 | C7: EURm
A8: Dette nette | B8: =Historical!G18 -> 2345 | C8: EURm
A9: Enterprise value de marche | B9: =B7+B8 -> 24421.018 | C9: EURm
A10: Taux sans risque France 10 ans | B10: 0.0368 | C10: %
A11: Prime de risque actions Eurozone | B11: 0.0575 | C11: %
A12: Beta Michelin | B12: 1 | C12: x
A13: Cout des fonds propres | B13: =B10+(B12*B11) -> 0.0943 | C13: %
A14: Cout de la dette avant impots | B14: 0.038 | C14: %
A15: Taux d'impot effectif | B15: 0.26293176 | C15: %
A16: Cout de la dette apres impots | B16: =B14*(1-B15) -> 0.028008593 | C16: %
A17: Poids fonds propres | B17: =B7/B9 -> 0.90397616 | C17: %
A18: Poids dette nette | B18: =B8/B9 -> 0.096023845 | C18: % | H18: .
A19: WACC retenu | B19: =(B13*B17)+(B16*B18) -> 0.087934444 | C19: %
A20: Croissance terminale | B20: 0.015 | C20: %

Sheet DCF
A1: Valorisation DCF
A2: FCFF 2026E-2030E + valeur terminale par croissance perpetuelle
B3: 2026E | C3: 2027E | D3: 2028E | E3: 2029E | F3: 2030E
A4: Chiffre d'affaires | B4: =Forecast!B4 -> 26382.06 | C4: =Forecast!C4 -> 27041.611 | D4: =Forecast!D4 -> 27852.86 | E4: =Forecast!E4 -> 28688.445 | F4: =Forecast!F4 -> 29405.656
A5: EBIT secteurs | B5: =Forecast!B9 -> 2822.8804 | C5: =Forecast!C9 -> 3028.6605 | D5: =Forecast!D9 -> 3230.9317 | E5: =Forecast!E9 -> 3413.925 | F5: =Forecast!F9 -> 3528.6788
A6: NOPAT | B6: =Forecast!B11 -> 2080.6555 | C6: =Forecast!C11 -> 2232.3294 | D6: =Forecast!D11 -> 2381.4171 | E6: =Forecast!E11 -> 2516.2957 | F6: =Forecast!F11 -> 2600.877
A7: D&A | B7: =Forecast!B13 -> 1925.8904 | C7: =Forecast!C13 -> 1946.996 | D7: =Forecast!D13 -> 1977.553 | E7: =Forecast!E13 -> 2008.1912 | F7: =Forecast!F13 -> 2058.396
A8: Capex | B8: =Forecast!B15 -> 1925.8904 | C8: =Forecast!C15 -> 1946.996 | D8: =Forecast!D15 -> 1977.553 | E8: =Forecast!E15 -> 2008.1912 | F8: =Forecast!F15 -> 2058.396
A9: Variation BFR | B9: =Forecast!B16 -> 3.8988266 | C9: =Forecast!C16 -> 6.5955149 | D9: =Forecast!D16 -> 8.1124834 | E9: =Forecast!E16 -> 8.3558579 | F9: =Forecast!F16 -> 7.1721113
A10: FCFF | B10: =Forecast!B17 -> 2076.7566 | C10: =Forecast!C17 -> 2225.7339 | D10: =Forecast!D17 -> 2373.3047 | E10: =Forecast!E17 -> 2507.9398 | F10: =Forecast!F17 -> 2593.7049
A11: Facteur d'actualisation | B11: =(1+WACC!$B$19)^-(COLUMN()-1) -> 0.91917303 | C11: =(1+WACC!$B$19)^-(COLUMN()-1) -> 0.84487906 | D11: =(1+WACC!$B$19)^-(COLUMN()-1) -> 0.77659005 | E11: =(1+WACC!$B$19)^-(COLUMN()-1) -> 0.71382063 | F11: =(1+WACC!$B$19)^-(COLUMN()-1) -> 0.65612467
A12: PV FCFF | B12: =B10*B11 -> 1908.8987 | C12: =C10*C11 -> 1880.476 | D12: =D10*D11 -> 1843.0848 | E12: =E10*E11 -> 1790.2192 | F12: =F10*F11 -> 1701.7938
A15: Synthese
A16: PV des FCFF explicites | B16: =SUM(B12:F12) -> 9124.4724
A17: Valeur terminale | B17: =F10*(1+WACC!$B$20)/(WACC!$B$19-WACC!$B$20) -> 36095.572
A18: PV valeur terminale | B18: =B17*F11 -> 23683.195
A19: Enterprise value DCF | B19: =B16+B18 -> 32807.668
A20: Dette nette | B20: =WACC!B8 -> 2345
A21: Equity value DCF | B21: =B19-B20 -> 30462.668
A22: Actions en circulation | B22: =WACC!B6 -> 684.74
A23: Valeur par action DCF | B23: =B21/B22 -> 44.487934
A24: Cours actuel | B24: =WACC!B5 -> 32.24
A25: Potentiel DCF | B25: =B23/B24-1 -> 0.37989869

Sheet Sensitivity
A1: Sensibilite DCF
A2: Valeur par action selon WACC et croissance terminale
A4: WACC \ g | B4: =WACC!$B$20-0.01 -> 0.005 | C4: =WACC!$B$20-0.005 -> 0.01 | D4: =WACC!$B$20 -> 0.015 | E4: =WACC!$B$20+0.005 -> 0.02 | F4: =WACC!$B$20+0.01 -> 0.025
A5: =WACC!$B$19-0.01 -> 0.077934444 | B5: =((DCF!$B$10/(1+$A5)^1)+(DCF!$C$10/(1+$A5)^2)+(DCF!$D$10/(1+$A5)^3)+(DCF!$E$10/(1+$A5)^4)+(DCF!$F$10/(1+$A5)^5)+((DCF!$F$10*(1+B$4))/($A5-B$4))/((1+$A5)^5)-WACC!$B$8)/WACC!$B$6 -> 46.133917 | C5: =((DCF!$B$10/(1+$A5)^1)+(DCF!$C$10/(1+$A5)^2)+(DCF!$D$10/(1+$A5)^3)+(DCF!$E$10/(1+$A5)^4)+(DCF!$F$10/(1+$A5)^5)+((DCF!$F$10*(1+C$4))/($A5-C$4))/((1+$A5)^5)-WACC!$B$8)/WACC!$B$6 -> 48.965132 | D5: =((DCF!$B$10/(1+$A5)^1)+(DCF!$C$10/(1+$A5)^2)+(DCF!$D$10/(1+$A5)^3)+(DCF!$E$10/(1+$A5)^4)+(DCF!$F$10/(1+$A5)^5)+((DCF!$F$10*(1+D$4))/($A5-D$4))/((1+$A5)^5)-WACC!$B$8)/WACC!$B$6 -> 52.246214 | E5: =((DCF!$B$10/(1+$A5)^1)+(DCF!$C$10/(1+$A5)^2)+(DCF!$D$10/(1+$A5)^3)+(DCF!$E$10/(1+$A5)^4)+(DCF!$F$10/(1+$A5)^5)+((DCF!$F$10*(1+E$4))/($A5-E$4))/((1+$A5)^5)-WACC!$B$8)/WACC!$B$6 -> 56.093639 | F5: =((DCF!$B$10/(1+$A5)^1)+(DCF!$C$10/(1+$A5)^2)+(DCF!$D$10/(1+$A5)^3)+(DCF!$E$10/(1+$A5)^4)+(DCF!$F$10/(1+$A5)^5)+((DCF!$F$10*(1+F$4))/($A5-F$4))/((1+$A5)^5)-WACC!$B$8)/WACC!$B$6 -> 60.667893
A6: =WACC!$B$19-0.005 -> 0.082934444 | B6: =((DCF!$B$10/(1+$A6)^1)+(DCF!$C$10/(1+$A6)^2)+(DCF!$D$10/(1+$A6)^3)+(DCF!$E$10/(1+$A6)^4)+(DCF!$F$10/(1+$A6)^5)+((DCF!$F$10*(1+B$4))/($A6-B$4))/((1+$A6)^5)-WACC!$B$8)/WACC!$B$6 -> 42.879052 | C6: =((DCF!$B$10/(1+$A6)^1)+(DCF!$C$10/(1+$A6)^2)+(DCF!$D$10/(1+$A6)^3)+(DCF!$E$10/(1+$A6)^4)+(DCF!$F$10/(1+$A6)^5)+((DCF!$F$10*(1+C$4))/($A6-C$4))/((1+$A6)^5)-WACC!$B$8)/WACC!$B$6 -> 45.301721 | D6: =((DCF!$B$10/(1+$A6)^1)+(DCF!$C$10/(1+$A6)^2)+(DCF!$D$10/(1+$A6)^3)+(DCF!$E$10/(1+$A6)^4)+(DCF!$F$10/(1+$A6)^5)+((DCF!$F$10*(1+D$4))/($A6-D$4))/((1+$A6)^5)-WACC!$B$8)/WACC!$B$6 -> 48.081009 | E6: =((DCF!$B$10/(1+$A6)^1)+(DCF!$C$10/(1+$A6)^2)+(DCF!$D$10/(1+$A6)^3)+(DCF!$E$10/(1+$A6)^4)+(DCF!$F$10/(1+$A6)^5)+((DCF!$F$10*(1+E$4))/($A6-E$4))/((1+$A6)^5)-WACC!$B$8)/WACC!$B$6 -> 51.301913 | F6: =((DCF!$B$10/(1+$A6)^1)+(DCF!$C$10/(1+$A6)^2)+(DCF!$D$10/(1+$A6)^3)+(DCF!$E$10/(1+$A6)^4)+(DCF!$F$10/(1+$A6)^5)+((DCF!$F$10*(1+F$4))/($A6-F$4))/((1+$A6)^5)-WACC!$B$8)/WACC!$B$6 -> 55.078774
A7: =WACC!$B$19 -> 0.087934444 | B7: =((DCF!$B$10/(1+$A7)^1)+(DCF!$C$10/(1+$A7)^2)+(DCF!$D$10/(1+$A7)^3)+(DCF!$E$10/(1+$A7)^4)+(DCF!$F$10/(1+$A7)^5)+((DCF!$F$10*(1+B$4))/($A7-B$4))/((1+$A7)^5)-WACC!$B$8)/WACC!$B$6 -> 40.017843 | C7: =((DCF!$B$10/(1+$A7)^1)+(DCF!$C$10/(1+$A7)^2)+(DCF!$D$10/(1+$A7)^3)+(DCF!$E$10/(1+$A7)^4)+(DCF!$F$10/(1+$A7)^5)+((DCF!$F$10*(1+C$4))/($A7-C$4))/((1+$A7)^5)-WACC!$B$8)/WACC!$B$6 -> 42.109496 | D7: =((DCF!$B$10/(1+$A7)^1)+(DCF!$C$10/(1+$A7)^2)+(DCF!$D$10/(1+$A7)^3)+(DCF!$E$10/(1+$A7)^4)+(DCF!$F$10/(1+$A7)^5)+((DCF!$F$10*(1+D$4))/($A7-D$4))/((1+$A7)^5)-WACC!$B$8)/WACC!$B$6 -> 44.487934 | E7: =((DCF!$B$10/(1+$A7)^1)+(DCF!$C$10/(1+$A7)^2)+(DCF!$D$10/(1+$A7)^3)+(DCF!$E$10/(1+$A7)^4)+(DCF!$F$10/(1+$A7)^5)+((DCF!$F$10*(1+E$4))/($A7-E$4))/((1+$A7)^5)-WACC!$B$8)/WACC!$B$6 -> 47.21648 | F7: =((DCF!$B$10/(1+$A7)^1)+(DCF!$C$10/(1+$A7)^2)+(DCF!$D$10/(1+$A7)^3)+(DCF!$E$10/(1+$A7)^4)+(DCF!$F$10/(1+$A7)^5)+((DCF!$F$10*(1+F$4))/($A7-F$4))/((1+$A7)^5)-WACC!$B$8)/WACC!$B$6 -> 50.378579
A8: =WACC!$B$19+0.005 -> 0.092934444 | B8: =((DCF!$B$10/(1+$A8)^1)+(DCF!$C$10/(1+$A8)^2)+(DCF!$D$10/(1+$A8)^3)+(DCF!$E$10/(1+$A8)^4)+(DCF!$F$10/(1+$A8)^5)+((DCF!$F$10*(1+B$4))/($A8-B$4))/((1+$A8)^5)-WACC!$B$8)/WACC!$B$6 -> 37.483114 | C8: =((DCF!$B$10/(1+$A8)^1)+(DCF!$C$10/(1+$A8)^2)+(DCF!$D$10/(1+$A8)^3)+(DCF!$E$10/(1+$A8)^4)+(DCF!$F$10/(1+$A8)^5)+((DCF!$F$10*(1+C$4))/($A8-C$4))/((1+$A8)^5)-WACC!$B$8)/WACC!$B$6 -> 39.30321 | D8: =((DCF!$B$10/(1+$A8)^1)+(DCF!$C$10/(1+$A8)^2)+(DCF!$D$10/(1+$A8)^3)+(DCF!$E$10/(1+$A8)^4)+(DCF!$F$10/(1+$A8)^5)+((DCF!$F$10*(1+D$4))/($A8-D$4))/((1+$A8)^5)-WACC!$B$8)/WACC!$B$6 -> 41.356849 | E8: =((DCF!$B$10/(1+$A8)^1)+(DCF!$C$10/(1+$A8)^2)+(DCF!$D$10/(1+$A8)^3)+(DCF!$E$10/(1+$A8)^4)+(DCF!$F$10/(1+$A8)^5)+((DCF!$F$10*(1+E$4))/($A8-E$4))/((1+$A8)^5)-WACC!$B$8)/WACC!$B$6 -> 43.692061 | F8: =((DCF!$B$10/(1+$A8)^1)+(DCF!$C$10/(1+$A8)^2)+(DCF!$D$10/(1+$A8)^3)+(DCF!$E$10/(1+$A8)^4)+(DCF!$F$10/(1+$A8)^5)+((DCF!$F$10*(1+F$4))/($A8-F$4))/((1+$A8)^5)-WACC!$B$8)/WACC!$B$6 -> 46.371018
A9: =WACC!$B$19+0.01 -> 0.097934444 | B9: =((DCF!$B$10/(1+$A9)^1)+(DCF!$C$10/(1+$A9)^2)+(DCF!$D$10/(1+$A9)^3)+(DCF!$E$10/(1+$A9)^4)+(DCF!$F$10/(1+$A9)^5)+((DCF!$F$10*(1+B$4))/($A9-B$4))/((1+$A9)^5)-WACC!$B$8)/WACC!$B$6 -> 35.222146 | C9: =((DCF!$B$10/(1+$A9)^1)+(DCF!$C$10/(1+$A9)^2)+(DCF!$D$10/(1+$A9)^3)+(DCF!$E$10/(1+$A9)^4)+(DCF!$F$10/(1+$A9)^5)+((DCF!$F$10*(1+C$4))/($A9-C$4))/((1+$A9)^5)-WACC!$B$8)/WACC!$B$6 -> 36.817009 | D9: =((DCF!$B$10/(1+$A9)^1)+(DCF!$C$10/(1+$A9)^2)+(DCF!$D$10/(1+$A9)^3)+(DCF!$E$10/(1+$A9)^4)+(DCF!$F$10/(1+$A9)^5)+((DCF!$F$10*(1+D$4))/($A9-D$4))/((1+$A9)^5)-WACC!$B$8)/WACC!$B$6 -> 38.604177 | E9: =((DCF!$B$10/(1+$A9)^1)+(DCF!$C$10/(1+$A9)^2)+(DCF!$D$10/(1+$A9)^3)+(DCF!$E$10/(1+$A9)^4)+(DCF!$F$10/(1+$A9)^5)+((DCF!$F$10*(1+E$4))/($A9-E$4))/((1+$A9)^5)-WACC!$B$8)/WACC!$B$6 -> 40.620661 | F9: =((DCF!$B$10/(1+$A9)^1)+(DCF!$C$10/(1+$A9)^2)+(DCF!$D$10/(1+$A9)^3)+(DCF!$E$10/(1+$A9)^4)+(DCF!$F$10/(1+$A9)^5)+((DCF!$F$10*(1+F$4))/($A9-F$4))/((1+$A9)^5)-WACC!$B$8)/WACC!$B$6 -> 42.913624

Sheet Football_Field
A1: Football field
A2: Synthese des valorisations par action
A4: Methode | B4: Bas | C4: Central | D4: Haut | E4: Commentaire
A5: Cours actuel | B5: =WACC!B5 -> 32.24 | C5: =WACC!B5 -> 32.24 | D5: =WACC!B5 -> 32.24 | E5: Reference marche StockAnalysis, 20 avril 2026
A6: Comparables | B6: =MIN(Comps!E13:E15) -> 23.545348 | C6: =AVERAGE(Comps!F13:F15) -> 36.069577 | D6: =MAX(Comps!G13:G15) -> 44.129049 | E6: Application quartiles / mediane aux metrics 2026E
A7: DCF | B7: =MIN(Sensitivity!B5:F9) -> 35.222146 | C7: =DCF!B23 -> 44.487934 | D7: =MAX(Sensitivity!B5:F9) -> 60.667893 | E7: Sensibilite WACC et croissance terminale
A8: Objectif retenu | B8: =AVERAGE(C6,C7) -> 40.278755 | C8: =AVERAGE(C6,C7) -> 40.278755 | D8: =AVERAGE(C6,C7) -> 40.278755 | E8: Moyenne du DCF central et des comparables centraux
